auto_vicuna_conversation_templates/__init__.py
auto_vicuna_conversation_templates-0.0.1.dist-info/METADATA
auto_vicuna_conversation_templates-0.0.1.dist-info/WHEEL
auto_vicuna_conversation_templates-0.0.1.dist-info/licenses/LICENSE
auto_vicuna_conversation_templates-0.0.1.dist-info/RECORD
